funsql/__init__.py
funsql/data/sql_keywords.txt
funsql/data/sql_templates.sql
funsql/src/pghook.py
funsql/src/template.py
funsql/tests/__init__.py
funsql/tests/test_funsql.py
funsql-0.25.data/data/keywords/sql_keywords.txt
funsql-0.25.data/data/templates/sql_templates.sql
funsql-0.25.dist-info/LICENSE
funsql-0.25.dist-info/METADATA
funsql-0.25.dist-info/WHEEL
funsql-0.25.dist-info/top_level.txt
funsql-0.25.dist-info/RECORD
